ordeq_common/__init__.py
ordeq_common/_version.py
ordeq_common/py.typed
ordeq_common/hooks/__init__.py
ordeq_common/hooks/logger.py
ordeq_common/hooks/spy.py
ordeq_common/io/__init__.py
ordeq_common/io/bytes_buffer.py
ordeq_common/io/dataclass.py
ordeq_common/io/iterate.py
ordeq_common/io/literal.py
ordeq_common/io/match.py
ordeq_common/io/printer.py
ordeq_common/io/string_buffer.py
ordeq_common-2.2.0.dist-info/licenses/LICENSE
ordeq_common-2.2.0.dist-info/METADATA
ordeq_common-2.2.0.dist-info/WHEEL
ordeq_common-2.2.0.dist-info/top_level.txt
ordeq_common-2.2.0.dist-info/RECORD
