Metadata-Version: 2.4
Name: ordeq_common
Version: 2.2.0
Summary: Frequently used IOs and Hooks for Ordeq projects
Author: Niels Neerhoff, Simon Brugman
Maintainer: Niels Neerhoff, Simon Brugman
License-Expression: MIT
Requires-Python: >=3.10
License-File: LICENSE
Requires-Dist: ordeq>=1.3.0
Dynamic: license-file
